<?xml version="1.0"?>
<ROIConfigData xmlns:xsd="http://www.w3.org/2001/XMLSchema" xmlns:xsi="http://www.w3.org/2001/XMLSchema-instance">
  <FormatVersion>120920</FormatVersion>
  <Guid>3c6e90bb-e7db-48ae-bf67-642712749a39</Guid>
  <Name>Obsidian Marinelli 0.5</Name>
  <LastUpdated>2024-05-29T17:11:25.7562297+03:00</LastUpdated>
  <ROIDefinitions>
    <ROIDefinitionData>
      <Name>K-40</Name>
      <Enabled>true</Enabled>
      <PeakEnergy>1460.75</PeakEnergy>
      <LowerLimit>1350</LowerLimit>
      <UpperLimit>1570</UpperLimit>
      <Color>#FF0000</Color>
      <BecquerelCoefficient>148740</BecquerelCoefficient>
      <BecquerelCoefficientError>10779.4008984078</BecquerelCoefficientError>
      <HalfLife>1277000000</HalfLife>
      <Intencity>10.66</Intencity>
      <Note />
      <ROIPrimitives>
        <ROISimpleDifferenceData>
          <PrimitiveType>BG difference</PrimitiveType>
          <OperationType>Addition</OperationType>
          <Coefficient>1</Coefficient>
          <CoefficientError>0</CoefficientError>
          <Note />
          <LowerLimit>1350</LowerLimit>
          <UpperLimit>1570</UpperLimit>
        </ROISimpleDifferenceData>
      </ROIPrimitives>
    </ROIDefinitionData>
    <ROIDefinitionData>
      <Name>Cs-137/Ba-137m</Name>
      <Enabled>false</Enabled>
      <PeakEnergy>661.66</PeakEnergy>
      <LowerLimit>562</LowerLimit>
      <UpperLimit>762</UpperLimit>
      <Color>#FF0000</Color>
      <BecquerelCoefficient>5548.52139304242</BecquerelCoefficient>
      <BecquerelCoefficientError>186.192286488109</BecquerelCoefficientError>
      <HalfLife>30</HalfLife>
      <Intencity>85.1</Intencity>
      <Note />
      <ROIPrimitives>
        <ROISimpleDifferenceData>
          <PrimitiveType>BG difference</PrimitiveType>
          <OperationType>Addition</OperationType>
          <Coefficient>1</Coefficient>
          <CoefficientError>0</CoefficientError>
          <Note />
          <LowerLimit>562</LowerLimit>
          <UpperLimit>762</UpperLimit>
        </ROISimpleDifferenceData>
      </ROIPrimitives>
    </ROIDefinitionData>
  </ROIDefinitions>
  <ROIEfficiency>
    <ROIEfficiencyData>
      <Energy>20</Energy>
      <Efficiency>1471.85</Efficiency>
      <ErrorPercent>554</ErrorPercent>
    </ROIEfficiencyData>
    <ROIEfficiencyData>
      <Energy>40</Energy>
      <Efficiency>0.00555793</Efficiency>
      <ErrorPercent>30.5</ErrorPercent>
    </ROIEfficiencyData>
    <ROIEfficiencyData>
      <Energy>60</Energy>
      <Efficiency>0.00319881</Efficiency>
      <ErrorPercent>1.01</ErrorPercent>
    </ROIEfficiencyData>
    <ROIEfficiencyData>
      <Energy>80</Energy>
      <Efficiency>0.00360372</Efficiency>
      <ErrorPercent>1.01</ErrorPercent>
    </ROIEfficiencyData>
    <ROIEfficiencyData>
      <Energy>100</Energy>
      <Efficiency>0.00378067</Efficiency>
      <ErrorPercent>1.02</ErrorPercent>
    </ROIEfficiencyData>
    <ROIEfficiencyData>
      <Energy>120</Energy>
      <Efficiency>0.00360473</Efficiency>
      <ErrorPercent>1.03</ErrorPercent>
    </ROIEfficiencyData>
    <ROIEfficiencyData>
      <Energy>140</Energy>
      <Efficiency>0.00323717</Efficiency>
      <ErrorPercent>0.966</ErrorPercent>
    </ROIEfficiencyData>
    <ROIEfficiencyData>
      <Energy>160</Energy>
      <Efficiency>0.00281629</Efficiency>
      <ErrorPercent>1.01</ErrorPercent>
    </ROIEfficiencyData>
    <ROIEfficiencyData>
      <Energy>180</Energy>
      <Efficiency>0.00241522</Efficiency>
      <ErrorPercent>1.13</ErrorPercent>
    </ROIEfficiencyData>
    <ROIEfficiencyData>
      <Energy>200</Energy>
      <Efficiency>0.00206242</Efficiency>
      <ErrorPercent>1.23</ErrorPercent>
    </ROIEfficiencyData>
    <ROIEfficiencyData>
      <Energy>220</Energy>
      <Efficiency>0.00176357</Efficiency>
      <ErrorPercent>1.29</ErrorPercent>
    </ROIEfficiencyData>
    <ROIEfficiencyData>
      <Energy>240</Energy>
      <Efficiency>0.00151472</Efficiency>
      <ErrorPercent>1.34</ErrorPercent>
    </ROIEfficiencyData>
    <ROIEfficiencyData>
      <Energy>260</Energy>
      <Efficiency>0.00130879</Efficiency>
      <ErrorPercent>1.4</ErrorPercent>
    </ROIEfficiencyData>
    <ROIEfficiencyData>
      <Energy>280</Energy>
      <Efficiency>0.0011384</Efficiency>
      <ErrorPercent>1.47</ErrorPercent>
    </ROIEfficiencyData>
    <ROIEfficiencyData>
      <Energy>300</Energy>
      <Efficiency>0.000996976</Efficiency>
      <ErrorPercent>1.56</ErrorPercent>
    </ROIEfficiencyData>
    <ROIEfficiencyData>
      <Energy>320</Energy>
      <Efficiency>0.000879001</Efficiency>
      <ErrorPercent>1.66</ErrorPercent>
    </ROIEfficiencyData>
    <ROIEfficiencyData>
      <Energy>340</Energy>
      <Efficiency>0.000780001</Efficiency>
      <ErrorPercent>1.77</ErrorPercent>
    </ROIEfficiencyData>
    <ROIEfficiencyData>
      <Energy>360</Energy>
      <Efficiency>0.000696391</Efficiency>
      <ErrorPercent>1.87</ErrorPercent>
    </ROIEfficiencyData>
    <ROIEfficiencyData>
      <Energy>380</Energy>
      <Efficiency>0.000625323</Efficiency>
      <ErrorPercent>1.96</ErrorPercent>
    </ROIEfficiencyData>
    <ROIEfficiencyData>
      <Energy>400</Energy>
      <Efficiency>0.000564529</Efficiency>
      <ErrorPercent>2.03</ErrorPercent>
    </ROIEfficiencyData>
    <ROIEfficiencyData>
      <Energy>420</Energy>
      <Efficiency>0.000512203</Efficiency>
      <ErrorPercent>2.1</ErrorPercent>
    </ROIEfficiencyData>
    <ROIEfficiencyData>
      <Energy>440</Energy>
      <Efficiency>0.0004669</Efficiency>
      <ErrorPercent>2.15</ErrorPercent>
    </ROIEfficiencyData>
    <ROIEfficiencyData>
      <Energy>460</Energy>
      <Efficiency>0.000427457</Efficiency>
      <ErrorPercent>2.2</ErrorPercent>
    </ROIEfficiencyData>
    <ROIEfficiencyData>
      <Energy>480</Energy>
      <Efficiency>0.000392935</Efficiency>
      <ErrorPercent>2.25</ErrorPercent>
    </ROIEfficiencyData>
    <ROIEfficiencyData>
      <Energy>500</Energy>
      <Efficiency>0.000362569</Efficiency>
      <ErrorPercent>2.31</ErrorPercent>
    </ROIEfficiencyData>
    <ROIEfficiencyData>
      <Energy>520</Energy>
      <Efficiency>0.000335733</Efficiency>
      <ErrorPercent>2.38</ErrorPercent>
    </ROIEfficiencyData>
    <ROIEfficiencyData>
      <Energy>540</Energy>
      <Efficiency>0.000311914</Efficiency>
      <ErrorPercent>2.46</ErrorPercent>
    </ROIEfficiencyData>
    <ROIEfficiencyData>
      <Energy>560</Energy>
      <Efficiency>0.000290685</Efficiency>
      <ErrorPercent>2.56</ErrorPercent>
    </ROIEfficiencyData>
    <ROIEfficiencyData>
      <Energy>580</Energy>
      <Efficiency>0.00027169</Efficiency>
      <ErrorPercent>2.68</ErrorPercent>
    </ROIEfficiencyData>
    <ROIEfficiencyData>
      <Energy>600</Energy>
      <Efficiency>0.000254634</Efficiency>
      <ErrorPercent>2.82</ErrorPercent>
    </ROIEfficiencyData>
    <ROIEfficiencyData>
      <Energy>620</Energy>
      <Efficiency>0.000239265</Efficiency>
      <ErrorPercent>2.98</ErrorPercent>
    </ROIEfficiencyData>
    <ROIEfficiencyData>
      <Energy>640</Energy>
      <Efficiency>0.000225372</Efficiency>
      <ErrorPercent>3.15</ErrorPercent>
    </ROIEfficiencyData>
    <ROIEfficiencyData>
      <Energy>660</Energy>
      <Efficiency>0.000212776</Efficiency>
      <ErrorPercent>3.34</ErrorPercent>
    </ROIEfficiencyData>
    <ROIEfficiencyData>
      <Energy>680</Energy>
      <Efficiency>0.000201322</Efficiency>
      <ErrorPercent>3.53</ErrorPercent>
    </ROIEfficiencyData>
    <ROIEfficiencyData>
      <Energy>700</Energy>
      <Efficiency>0.00019088</Efficiency>
      <ErrorPercent>3.74</ErrorPercent>
    </ROIEfficiencyData>
    <ROIEfficiencyData>
      <Energy>720</Energy>
      <Efficiency>0.000181335</Efficiency>
      <ErrorPercent>3.95</ErrorPercent>
    </ROIEfficiencyData>
    <ROIEfficiencyData>
      <Energy>740</Energy>
      <Efficiency>0.000172589</Efficiency>
      <ErrorPercent>4.16</ErrorPercent>
    </ROIEfficiencyData>
    <ROIEfficiencyData>
      <Energy>760</Energy>
      <Efficiency>0.000164558</Efficiency>
      <ErrorPercent>4.37</ErrorPercent>
    </ROIEfficiencyData>
    <ROIEfficiencyData>
      <Energy>780</Energy>
      <Efficiency>0.000157166</Efficiency>
      <ErrorPercent>4.58</ErrorPercent>
    </ROIEfficiencyData>
    <ROIEfficiencyData>
      <Energy>800</Energy>
      <Efficiency>0.00015035</Efficiency>
      <ErrorPercent>4.78</ErrorPercent>
    </ROIEfficiencyData>
    <ROIEfficiencyData>
      <Energy>820</Energy>
      <Efficiency>0.000144051</Efficiency>
      <ErrorPercent>4.98</ErrorPercent>
    </ROIEfficiencyData>
    <ROIEfficiencyData>
      <Energy>840</Energy>
      <Efficiency>0.000138221</Efficiency>
      <ErrorPercent>5.16</ErrorPercent>
    </ROIEfficiencyData>
    <ROIEfficiencyData>
      <Energy>860</Energy>
      <Efficiency>0.000132814</Efficiency>
      <ErrorPercent>5.34</ErrorPercent>
    </ROIEfficiencyData>
    <ROIEfficiencyData>
      <Energy>880</Energy>
      <Efficiency>0.000127791</Efficiency>
      <ErrorPercent>5.52</ErrorPercent>
    </ROIEfficiencyData>
    <ROIEfficiencyData>
      <Energy>900</Energy>
      <Efficiency>0.000123117</Efficiency>
      <ErrorPercent>5.68</ErrorPercent>
    </ROIEfficiencyData>
    <ROIEfficiencyData>
      <Energy>920</Energy>
      <Efficiency>0.000118762</Efficiency>
      <ErrorPercent>5.83</ErrorPercent>
    </ROIEfficiencyData>
    <ROIEfficiencyData>
      <Energy>940</Energy>
      <Efficiency>0.000114698</Efficiency>
      <ErrorPercent>5.96</ErrorPercent>
    </ROIEfficiencyData>
    <ROIEfficiencyData>
      <Energy>960</Energy>
      <Efficiency>0.0001109</Efficiency>
      <ErrorPercent>6.09</ErrorPercent>
    </ROIEfficiencyData>
    <ROIEfficiencyData>
      <Energy>980</Energy>
      <Efficiency>0.000107346</Efficiency>
      <ErrorPercent>6.21</ErrorPercent>
    </ROIEfficiencyData>
    <ROIEfficiencyData>
      <Energy>1000</Energy>
      <Efficiency>0.000104015</Efficiency>
      <ErrorPercent>6.31</ErrorPercent>
    </ROIEfficiencyData>
    <ROIEfficiencyData>
      <Energy>1020</Energy>
      <Efficiency>0.00010089</Efficiency>
      <ErrorPercent>6.41</ErrorPercent>
    </ROIEfficiencyData>
    <ROIEfficiencyData>
      <Energy>1040</Energy>
      <Efficiency>9.79546E-05</Efficiency>
      <ErrorPercent>6.49</ErrorPercent>
    </ROIEfficiencyData>
    <ROIEfficiencyData>
      <Energy>1060</Energy>
      <Efficiency>9.5194E-05</Efficiency>
      <ErrorPercent>6.56</ErrorPercent>
    </ROIEfficiencyData>
    <ROIEfficiencyData>
      <Energy>1080</Energy>
      <Efficiency>9.25949E-05</Efficiency>
      <ErrorPercent>6.63</ErrorPercent>
    </ROIEfficiencyData>
    <ROIEfficiencyData>
      <Energy>1100</Energy>
      <Efficiency>9.01451E-05</Efficiency>
      <ErrorPercent>6.68</ErrorPercent>
    </ROIEfficiencyData>
    <ROIEfficiencyData>
      <Energy>1120</Energy>
      <Efficiency>8.78336E-05</Efficiency>
      <ErrorPercent>6.73</ErrorPercent>
    </ROIEfficiencyData>
    <ROIEfficiencyData>
      <Energy>1140</Energy>
      <Efficiency>8.56505E-05</Efficiency>
      <ErrorPercent>6.77</ErrorPercent>
    </ROIEfficiencyData>
    <ROIEfficiencyData>
      <Energy>1160</Energy>
      <Efficiency>8.35864E-05</Efficiency>
      <ErrorPercent>6.8</ErrorPercent>
    </ROIEfficiencyData>
    <ROIEfficiencyData>
      <Energy>1180</Energy>
      <Efficiency>8.16331E-05</Efficiency>
      <ErrorPercent>6.83</ErrorPercent>
    </ROIEfficiencyData>
    <ROIEfficiencyData>
      <Energy>1200</Energy>
      <Efficiency>7.97828E-05</Efficiency>
      <ErrorPercent>6.85</ErrorPercent>
    </ROIEfficiencyData>
    <ROIEfficiencyData>
      <Energy>1220</Energy>
      <Efficiency>7.80285E-05</Efficiency>
      <ErrorPercent>6.87</ErrorPercent>
    </ROIEfficiencyData>
    <ROIEfficiencyData>
      <Energy>1240</Energy>
      <Efficiency>7.63637E-05</Efficiency>
      <ErrorPercent>6.89</ErrorPercent>
    </ROIEfficiencyData>
    <ROIEfficiencyData>
      <Energy>1260</Energy>
      <Efficiency>7.47825E-05</Efficiency>
      <ErrorPercent>6.9</ErrorPercent>
    </ROIEfficiencyData>
    <ROIEfficiencyData>
      <Energy>1280</Energy>
      <Efficiency>7.32793E-05</Efficiency>
      <ErrorPercent>6.92</ErrorPercent>
    </ROIEfficiencyData>
    <ROIEfficiencyData>
      <Energy>1300</Energy>
      <Efficiency>7.18491E-05</Efficiency>
      <ErrorPercent>6.93</ErrorPercent>
    </ROIEfficiencyData>
    <ROIEfficiencyData>
      <Energy>1320</Energy>
      <Efficiency>7.04871E-05</Efficiency>
      <ErrorPercent>6.95</ErrorPercent>
    </ROIEfficiencyData>
    <ROIEfficiencyData>
      <Energy>1340</Energy>
      <Efficiency>6.91892E-05</Efficiency>
      <ErrorPercent>6.97</ErrorPercent>
    </ROIEfficiencyData>
    <ROIEfficiencyData>
      <Energy>1360</Energy>
      <Efficiency>6.79512E-05</Efficiency>
      <ErrorPercent>6.99</ErrorPercent>
    </ROIEfficiencyData>
    <ROIEfficiencyData>
      <Energy>1380</Energy>
      <Efficiency>6.67694E-05</Efficiency>
      <ErrorPercent>7.02</ErrorPercent>
    </ROIEfficiencyData>
    <ROIEfficiencyData>
      <Energy>1400</Energy>
      <Efficiency>6.56404E-05</Efficiency>
      <ErrorPercent>7.05</ErrorPercent>
    </ROIEfficiencyData>
    <ROIEfficiencyData>
      <Energy>1420</Energy>
      <Efficiency>6.45609E-05</Efficiency>
      <ErrorPercent>7.09</ErrorPercent>
    </ROIEfficiencyData>
    <ROIEfficiencyData>
      <Energy>1440</Energy>
      <Efficiency>6.35279E-05</Efficiency>
      <ErrorPercent>7.13</ErrorPercent>
    </ROIEfficiencyData>
    <ROIEfficiencyData>
      <Energy>1460</Energy>
      <Efficiency>6.25387E-05</Efficiency>
      <ErrorPercent>7.18</ErrorPercent>
    </ROIEfficiencyData>
    <ROIEfficiencyData>
      <Energy>1480</Energy>
      <Efficiency>6.15907E-05</Efficiency>
      <ErrorPercent>7.24</ErrorPercent>
    </ROIEfficiencyData>
    <ROIEfficiencyData>
      <Energy>1500</Energy>
      <Efficiency>6.06813E-05</Efficiency>
      <ErrorPercent>7.31</ErrorPercent>
    </ROIEfficiencyData>
    <ROIEfficiencyData>
      <Energy>1520</Energy>
      <Efficiency>5.98084E-05</Efficiency>
      <ErrorPercent>7.38</ErrorPercent>
    </ROIEfficiencyData>
    <ROIEfficiencyData>
      <Energy>1540</Energy>
      <Efficiency>5.89698E-05</Efficiency>
      <ErrorPercent>7.47</ErrorPercent>
    </ROIEfficiencyData>
    <ROIEfficiencyData>
      <Energy>1560</Energy>
      <Efficiency>5.81635E-05</Efficiency>
      <ErrorPercent>7.56</ErrorPercent>
    </ROIEfficiencyData>
    <ROIEfficiencyData>
      <Energy>1580</Energy>
      <Efficiency>5.73876E-05</Efficiency>
      <ErrorPercent>7.66</ErrorPercent>
    </ROIEfficiencyData>
    <ROIEfficiencyData>
      <Energy>1600</Energy>
      <Efficiency>5.66404E-05</Efficiency>
      <ErrorPercent>7.77</ErrorPercent>
    </ROIEfficiencyData>
    <ROIEfficiencyData>
      <Energy>1620</Energy>
      <Efficiency>5.59203E-05</Efficiency>
      <ErrorPercent>7.88</ErrorPercent>
    </ROIEfficiencyData>
    <ROIEfficiencyData>
      <Energy>1640</Energy>
      <Efficiency>5.52256E-05</Efficiency>
      <ErrorPercent>8</ErrorPercent>
    </ROIEfficiencyData>
    <ROIEfficiencyData>
      <Energy>1660</Energy>
      <Efficiency>5.45549E-05</Efficiency>
      <ErrorPercent>8.13</ErrorPercent>
    </ROIEfficiencyData>
    <ROIEfficiencyData>
      <Energy>1680</Energy>
      <Efficiency>5.39068E-05</Efficiency>
      <ErrorPercent>8.27</ErrorPercent>
    </ROIEfficiencyData>
    <ROIEfficiencyData>
      <Energy>1700</Energy>
      <Efficiency>5.328E-05</Efficiency>
      <ErrorPercent>8.41</ErrorPercent>
    </ROIEfficiencyData>
    <ROIEfficiencyData>
      <Energy>1720</Energy>
      <Efficiency>5.26734E-05</Efficiency>
      <ErrorPercent>8.55</ErrorPercent>
    </ROIEfficiencyData>
    <ROIEfficiencyData>
      <Energy>1740</Energy>
      <Efficiency>5.20856E-05</Efficiency>
      <ErrorPercent>8.7</ErrorPercent>
    </ROIEfficiencyData>
    <ROIEfficiencyData>
      <Energy>1760</Energy>
      <Efficiency>5.15158E-05</Efficiency>
      <ErrorPercent>8.85</ErrorPercent>
    </ROIEfficiencyData>
    <ROIEfficiencyData>
      <Energy>1780</Energy>
      <Efficiency>5.09627E-05</Efficiency>
      <ErrorPercent>9</ErrorPercent>
    </ROIEfficiencyData>
    <ROIEfficiencyData>
      <Energy>1800</Energy>
      <Efficiency>5.04254E-05</Efficiency>
      <ErrorPercent>9.15</ErrorPercent>
    </ROIEfficiencyData>
    <ROIEfficiencyData>
      <Energy>1820</Energy>
      <Efficiency>4.99031E-05</Efficiency>
      <ErrorPercent>9.31</ErrorPercent>
    </ROIEfficiencyData>
    <ROIEfficiencyData>
      <Energy>1840</Energy>
      <Efficiency>4.93948E-05</Efficiency>
      <ErrorPercent>9.46</ErrorPercent>
    </ROIEfficiencyData>
    <ROIEfficiencyData>
      <Energy>1860</Energy>
      <Efficiency>4.88996E-05</Efficiency>
      <ErrorPercent>9.61</ErrorPercent>
    </ROIEfficiencyData>
    <ROIEfficiencyData>
      <Energy>1880</Energy>
      <Efficiency>4.84168E-05</Efficiency>
      <ErrorPercent>9.76</ErrorPercent>
    </ROIEfficiencyData>
    <ROIEfficiencyData>
      <Energy>1900</Energy>
      <Efficiency>4.79457E-05</Efficiency>
      <ErrorPercent>9.91</ErrorPercent>
    </ROIEfficiencyData>
    <ROIEfficiencyData>
      <Energy>1920</Energy>
      <Efficiency>4.74855E-05</Efficiency>
      <ErrorPercent>10.1</ErrorPercent>
    </ROIEfficiencyData>
    <ROIEfficiencyData>
      <Energy>1940</Energy>
      <Efficiency>4.70355E-05</Efficiency>
      <ErrorPercent>10.2</ErrorPercent>
    </ROIEfficiencyData>
    <ROIEfficiencyData>
      <Energy>1960</Energy>
      <Efficiency>4.65951E-05</Efficiency>
      <ErrorPercent>10.3</ErrorPercent>
    </ROIEfficiencyData>
    <ROIEfficiencyData>
      <Energy>1980</Energy>
      <Efficiency>4.61638E-05</Efficiency>
      <ErrorPercent>10.5</ErrorPercent>
    </ROIEfficiencyData>
    <ROIEfficiencyData>
      <Energy>2000</Energy>
      <Efficiency>4.57408E-05</Efficiency>
      <ErrorPercent>10.6</ErrorPercent>
    </ROIEfficiencyData>
    <ROIEfficiencyData>
      <Energy>2020</Energy>
      <Efficiency>4.53256E-05</Efficiency>
      <ErrorPercent>10.7</ErrorPercent>
    </ROIEfficiencyData>
    <ROIEfficiencyData>
      <Energy>2040</Energy>
      <Efficiency>4.49178E-05</Efficiency>
      <ErrorPercent>10.8</ErrorPercent>
    </ROIEfficiencyData>
    <ROIEfficiencyData>
      <Energy>2060</Energy>
      <Efficiency>4.45168E-05</Efficiency>
      <ErrorPercent>10.9</ErrorPercent>
    </ROIEfficiencyData>
    <ROIEfficiencyData>
      <Energy>2080</Energy>
      <Efficiency>4.41221E-05</Efficiency>
      <ErrorPercent>11</ErrorPercent>
    </ROIEfficiencyData>
    <ROIEfficiencyData>
      <Energy>2100</Energy>
      <Efficiency>4.37332E-05</Efficiency>
      <ErrorPercent>11.1</ErrorPercent>
    </ROIEfficiencyData>
    <ROIEfficiencyData>
      <Energy>2120</Energy>
      <Efficiency>4.33499E-05</Efficiency>
      <ErrorPercent>11.2</ErrorPercent>
    </ROIEfficiencyData>
    <ROIEfficiencyData>
      <Energy>2140</Energy>
      <Efficiency>4.29715E-05</Efficiency>
      <ErrorPercent>11.2</ErrorPercent>
    </ROIEfficiencyData>
    <ROIEfficiencyData>
      <Energy>2160</Energy>
      <Efficiency>4.25978E-05</Efficiency>
      <ErrorPercent>11.3</ErrorPercent>
    </ROIEfficiencyData>
    <ROIEfficiencyData>
      <Energy>2180</Energy>
      <Efficiency>4.22284E-05</Efficiency>
      <ErrorPercent>11.3</ErrorPercent>
    </ROIEfficiencyData>
    <ROIEfficiencyData>
      <Energy>2200</Energy>
      <Efficiency>4.18629E-05</Efficiency>
      <ErrorPercent>11.3</ErrorPercent>
    </ROIEfficiencyData>
    <ROIEfficiencyData>
      <Energy>2220</Energy>
      <Efficiency>4.15009E-05</Efficiency>
      <ErrorPercent>11.4</ErrorPercent>
    </ROIEfficiencyData>
    <ROIEfficiencyData>
      <Energy>2240</Energy>
      <Efficiency>4.11422E-05</Efficiency>
      <ErrorPercent>11.4</ErrorPercent>
    </ROIEfficiencyData>
    <ROIEfficiencyData>
      <Energy>2260</Energy>
      <Efficiency>4.07864E-05</Efficiency>
      <ErrorPercent>11.4</ErrorPercent>
    </ROIEfficiencyData>
    <ROIEfficiencyData>
      <Energy>2280</Energy>
      <Efficiency>4.04333E-05</Efficiency>
      <ErrorPercent>11.3</ErrorPercent>
    </ROIEfficiencyData>
    <ROIEfficiencyData>
      <Energy>2300</Energy>
      <Efficiency>4.00826E-05</Efficiency>
      <ErrorPercent>11.3</ErrorPercent>
    </ROIEfficiencyData>
    <ROIEfficiencyData>
      <Energy>2320</Energy>
      <Efficiency>3.9734E-05</Efficiency>
      <ErrorPercent>11.3</ErrorPercent>
    </ROIEfficiencyData>
    <ROIEfficiencyData>
      <Energy>2340</Energy>
      <Efficiency>3.93873E-05</Efficiency>
      <ErrorPercent>11.2</ErrorPercent>
    </ROIEfficiencyData>
    <ROIEfficiencyData>
      <Energy>2360</Energy>
      <Efficiency>3.90422E-05</Efficiency>
      <ErrorPercent>11.1</ErrorPercent>
    </ROIEfficiencyData>
    <ROIEfficiencyData>
      <Energy>2380</Energy>
      <Efficiency>3.86985E-05</Efficiency>
      <ErrorPercent>11</ErrorPercent>
    </ROIEfficiencyData>
    <ROIEfficiencyData>
      <Energy>2400</Energy>
      <Efficiency>3.83561E-05</Efficiency>
      <ErrorPercent>10.9</ErrorPercent>
    </ROIEfficiencyData>
    <ROIEfficiencyData>
      <Energy>2420</Energy>
      <Efficiency>3.80147E-05</Efficiency>
      <ErrorPercent>10.8</ErrorPercent>
    </ROIEfficiencyData>
    <ROIEfficiencyData>
      <Energy>2440</Energy>
      <Efficiency>3.76741E-05</Efficiency>
      <ErrorPercent>10.7</ErrorPercent>
    </ROIEfficiencyData>
    <ROIEfficiencyData>
      <Energy>2460</Energy>
      <Efficiency>3.73342E-05</Efficiency>
      <ErrorPercent>10.6</ErrorPercent>
    </ROIEfficiencyData>
    <ROIEfficiencyData>
      <Energy>2480</Energy>
      <Efficiency>3.69947E-05</Efficiency>
      <ErrorPercent>10.4</ErrorPercent>
    </ROIEfficiencyData>
    <ROIEfficiencyData>
      <Energy>2500</Energy>
      <Efficiency>3.66557E-05</Efficiency>
      <ErrorPercent>10.3</ErrorPercent>
    </ROIEfficiencyData>
    <ROIEfficiencyData>
      <Energy>2520</Energy>
      <Efficiency>3.63168E-05</Efficiency>
      <ErrorPercent>10.1</ErrorPercent>
    </ROIEfficiencyData>
    <ROIEfficiencyData>
      <Energy>2540</Energy>
      <Efficiency>3.59781E-05</Efficiency>
      <ErrorPercent>9.92</ErrorPercent>
    </ROIEfficiencyData>
    <ROIEfficiencyData>
      <Energy>2560</Energy>
      <Efficiency>3.56393E-05</Efficiency>
      <ErrorPercent>9.74</ErrorPercent>
    </ROIEfficiencyData>
    <ROIEfficiencyData>
      <Energy>2580</Energy>
      <Efficiency>3.53004E-05</Efficiency>
      <ErrorPercent>9.54</ErrorPercent>
    </ROIEfficiencyData>
    <ROIEfficiencyData>
      <Energy>2600</Energy>
      <Efficiency>3.49612E-05</Efficiency>
      <ErrorPercent>9.35</ErrorPercent>
    </ROIEfficiencyData>
    <ROIEfficiencyData>
      <Energy>2620</Energy>
      <Efficiency>3.46217E-05</Efficiency>
      <ErrorPercent>9.15</ErrorPercent>
    </ROIEfficiencyData>
    <ROIEfficiencyData>
      <Energy>2640</Energy>
      <Efficiency>3.42818E-05</Efficiency>
      <ErrorPercent>8.96</ErrorPercent>
    </ROIEfficiencyData>
    <ROIEfficiencyData>
      <Energy>2660</Energy>
      <Efficiency>3.39414E-05</Efficiency>
      <ErrorPercent>8.76</ErrorPercent>
    </ROIEfficiencyData>
    <ROIEfficiencyData>
      <Energy>2680</Energy>
      <Efficiency>3.36004E-05</Efficiency>
      <ErrorPercent>8.58</ErrorPercent>
    </ROIEfficiencyData>
    <ROIEfficiencyData>
      <Energy>2700</Energy>
      <Efficiency>3.32588E-05</Efficiency>
      <ErrorPercent>8.41</ErrorPercent>
    </ROIEfficiencyData>
    <ROIEfficiencyData>
      <Energy>2720</Energy>
      <Efficiency>3.29166E-05</Efficiency>
      <ErrorPercent>8.26</ErrorPercent>
    </ROIEfficiencyData>
    <ROIEfficiencyData>
      <Energy>2740</Energy>
      <Efficiency>3.25737E-05</Efficiency>
      <ErrorPercent>8.13</ErrorPercent>
    </ROIEfficiencyData>
    <ROIEfficiencyData>
      <Energy>2760</Energy>
      <Efficiency>3.223E-05</Efficiency>
      <ErrorPercent>8.03</ErrorPercent>
    </ROIEfficiencyData>
    <ROIEfficiencyData>
      <Energy>2780</Energy>
      <Efficiency>3.18856E-05</Efficiency>
      <ErrorPercent>7.97</ErrorPercent>
    </ROIEfficiencyData>
    <ROIEfficiencyData>
      <Energy>2800</Energy>
      <Efficiency>3.15404E-05</Efficiency>
      <ErrorPercent>7.95</ErrorPercent>
    </ROIEfficiencyData>
    <ROIEfficiencyData>
      <Energy>2820</Energy>
      <Efficiency>3.11944E-05</Efficiency>
      <ErrorPercent>7.98</ErrorPercent>
    </ROIEfficiencyData>
    <ROIEfficiencyData>
      <Energy>2840</Energy>
      <Efficiency>3.08475E-05</Efficiency>
      <ErrorPercent>8.06</ErrorPercent>
    </ROIEfficiencyData>
    <ROIEfficiencyData>
      <Energy>2860</Energy>
      <Efficiency>3.04999E-05</Efficiency>
      <ErrorPercent>8.21</ErrorPercent>
    </ROIEfficiencyData>
    <ROIEfficiencyData>
      <Energy>2880</Energy>
      <Efficiency>3.01515E-05</Efficiency>
      <ErrorPercent>8.41</ErrorPercent>
    </ROIEfficiencyData>
    <ROIEfficiencyData>
      <Energy>2900</Energy>
      <Efficiency>2.98024E-05</Efficiency>
      <ErrorPercent>8.69</ErrorPercent>
    </ROIEfficiencyData>
    <ROIEfficiencyData>
      <Energy>2920</Energy>
      <Efficiency>2.94524E-05</Efficiency>
      <ErrorPercent>9.02</ErrorPercent>
    </ROIEfficiencyData>
    <ROIEfficiencyData>
      <Energy>2940</Energy>
      <Efficiency>2.91017E-05</Efficiency>
      <ErrorPercent>9.43</ErrorPercent>
    </ROIEfficiencyData>
    <ROIEfficiencyData>
      <Energy>2960</Energy>
      <Efficiency>2.87504E-05</Efficiency>
      <ErrorPercent>9.9</ErrorPercent>
    </ROIEfficiencyData>
    <ROIEfficiencyData>
      <Energy>2980</Energy>
      <Efficiency>2.83983E-05</Efficiency>
      <ErrorPercent>10.4</ErrorPercent>
    </ROIEfficiencyData>
    <ROIEfficiencyData>
      <Energy>3000</Energy>
      <Efficiency>2.80456E-05</Efficiency>
      <ErrorPercent>11</ErrorPercent>
    </ROIEfficiencyData>
  </ROIEfficiency>
  <Note />
</ROIConfigData>